atrends/__init__.py
atrends/config.py
atrends/data_fetcher.py
atrends/plotter.py
atrends-0.1.4.dist-info/WHEEL
atrends-0.1.4.dist-info/METADATA
atrends-0.1.4.dist-info/RECORD
